AUTHORS.rst
CONTRIBUTING.rst
HISTORY.rst
LICENSE
MANIFEST.in
README.rst
setup.cfg
setup.py
GBSCA_pro/GBSCA_pro.py
GBSCA_pro/__init__.py
GBSCA_pro/helper.py
GBSCA_pro.egg-info/PKG-INFO
GBSCA_pro.egg-info/SOURCES.txt
GBSCA_pro.egg-info/dependency_links.txt
GBSCA_pro.egg-info/not-zip-safe
GBSCA_pro.egg-info/top_level.txt
docs/Makefile
docs/authors.rst
docs/conf.py
docs/contributing.rst
docs/history.rst
docs/index.rst
docs/installation.rst
docs/make.bat
docs/readme.rst
docs/usage.rst
tests/__init__.py
tests/test_GBSCA_pro.py