Metadata-Version: 1.2
Name: GBSCA-pro
Version: 0.1.0
Summary: remove redundancy in a collections of sequences.
Home-page: https://github.com/chenpoi/GBSCA_pro
Author: Mengqi Chen
Author-email: chen.meng@husky.neu.edu
License: MIT license
Keywords: GBSCA_pro
Platform: UNKNOWN
Classifier: Development Status :: 2 - Pre-Alpha
Classifier: Intended Audience :: Developers
Classifier: License :: OSI Approved :: MIT License
Classifier: Natural Language :: English
Classifier: Programming Language :: Python :: 3
Classifier: Programming Language :: Python :: 3.5
Classifier: Programming Language :: Python :: 3.6
Classifier: Programming Language :: Python :: 3.7
Classifier: Programming Language :: Python :: 3.8
Requires-Python: >=3.5
